natural_python/__init__.py
natural_python/__main__.py
natural_python/console.py
natural_python/interpreter.py
natural_python/language_model_api.py
natural_python-0.1.8.dist-info/entry_points.txt
natural_python-0.1.8.dist-info/WHEEL
natural_python-0.1.8.dist-info/METADATA
natural_python-0.1.8.dist-info/RECORD
