Metadata-Version: 2.1
Name: natural-python
Version: 0.1.8
Summary: 
Author: Leo
Author-email: leohdz.c0@gmail.com
Requires-Python: >=3.10,<4.0
Classifier: Programming Language :: Python :: 3
Classifier: Programming Language :: Python :: 3.10
Requires-Dist: openai (>=0.26.5,<0.27.0)
